swaig_cli/__init__.py
swaig_cli/cli.py
usr/local/share/man/man1/swaig_cli.1
swaig_cli-0.1.5.dist-info/METADATA
swaig_cli-0.1.5.dist-info/WHEEL
swaig_cli-0.1.5.dist-info/entry_points.txt
swaig_cli-0.1.5.dist-info/top_level.txt
swaig_cli-0.1.5.dist-info/RECORD
