Metadata-Version: 2.1
Name: swaig-cli
Version: 0.1.5
Summary: A command-line tool for testing SignalWire AI Gateway functions
Home-page: https://github.com/briankwest/swaig-cli
Author: Brian West
Author-email: brian@signalwire.com
License: MIT
Classifier: Programming Language :: Python :: 3
Classifier: License :: OSI Approved :: MIT License
Classifier: Operating System :: OS Independent
Requires-Python: >=3.8
Requires-Dist: requests
Requires-Dist: wheel
